polyversion/__init__.py
polyversion/__main__.py
polyversion/setuplugin.py
polyversion-0.2.2a1.dist-info/LICENSE.txt
polyversion-0.2.2a1.dist-info/METADATA
polyversion-0.2.2a1.dist-info/RECORD
polyversion-0.2.2a1.dist-info/WHEEL
polyversion-0.2.2a1.dist-info/entry_points.txt
polyversion-0.2.2a1.dist-info/top_level.txt
polyversion-0.2.2a1.dist-info/zip-safe
