Metadata-Version: 2.1
Name: polyversion
Version: 0.2.2a1
Summary: Polyvers's lib to derive subproject versions from tags on Git monorepos.
Home-page: https://github.com/jrcstu/polyvers
Author: Kostis Anagnostopoulos
Author-email: ankostis@gmail.com
License: MIT
Download-URL: https://pypi.org/project/polyversion/
Project-URL: Documentation, http://polyvers.readthedocs.io/en/latest/usage-pvlib.html
Project-URL: Source, https://github.com/jrcstu/polyvers
Project-URL: Tracker, https://github.com/jrcstu/polyvers/issues
Keywords: version-management,configuration-management,versioning,git,monorepo,tool,library
Platform: any
Classifier: Development Status :: 3 - Alpha
Classifier: Intended Audience :: Developers
Classifier: License :: OSI Approved :: MIT License
Classifier: Natural Language :: English
Classifier: Programming Language :: Python :: 2
Classifier: Programming Language :: Python :: 2.6
Classifier: Programming Language :: Python :: 3
Classifier: Programming Language :: Python :: 3.4
Classifier: Programming Language :: Python :: 3.5
Classifier: Programming Language :: Python :: 3.6
Classifier: Programming Language :: Python :: 3.7
Provides-Extra: test
Provides-Extra: test
Requires-Dist: pytest; extra == 'test'
Requires-Dist: pytest-runner; extra == 'test'
Requires-Dist: pytest-cov; extra == 'test'
Requires-Dist: flake8; extra == 'test'
Requires-Dist: flake8-builtins; extra == 'test'
Requires-Dist: flake8-mutable; extra == 'test'
